voice_agent/__init__.py
voice_agent/cli.py
voice_agent/config.py
voice_agent/py.typed
voice_agent/server.py
voice_agent/core/__init__.py
voice_agent/core/agent.py
voice_agent/core/streaming.py
voice_agent/core/types.py
voice_agent/llm/__init__.py
voice_agent/llm/llm.py
voice_agent/stt/__init__.py
voice_agent/stt/stt.py
voice_agent/tts/__init__.py
voice_agent/tts/tts.py
fastrtc_voice_agent-0.2.1.dist-info/METADATA
fastrtc_voice_agent-0.2.1.dist-info/WHEEL
fastrtc_voice_agent-0.2.1.dist-info/entry_points.txt
fastrtc_voice_agent-0.2.1.dist-info/RECORD
