Metadata-Version: 2.4
Name: fastrtc-voice-agent
Version: 0.2.1
Summary: A modular voice agent with swappable STT/TTS/LLM backends
Project-URL: Repository, https://github.com/SonDePoisson/voice-agent
Author: Clement Poisson
License: MIT
Keywords: agent,edge-tts,fastrtc,llm,stt,tts,voice,whisper
Classifier: Development Status :: 3 - Alpha
Classifier: Intended Audience :: Developers
Classifier: License :: OSI Approved :: MIT License
Classifier: Programming Language :: Python :: 3.12
Classifier: Topic :: Multimedia :: Sound/Audio :: Speech
Requires-Python: >=3.12
Requires-Dist: anthropic>=0.40.0
Requires-Dist: dotenv>=0.9.9
Requires-Dist: edge-tts>=7.2.7
Requires-Dist: faster-whisper>=1.2.1
Requires-Dist: fastrtc[vad]>=0.0.34
Requires-Dist: groq>=1.0.0
Requires-Dist: librosa>=0.10
Requires-Dist: numpy>=1.24
Requires-Dist: ollama>=0.6.1
Requires-Dist: pip>=25.3
Requires-Dist: pydub>=0.25.1
Requires-Dist: python-dotenv>=1.0.0
Requires-Dist: twine>=6.2.0
Provides-Extra: all
Requires-Dist: anthropic>=0.40.0; extra == 'all'
Requires-Dist: groq>=0.11.0; extra == 'all'
Requires-Dist: openai-whisper>=20250625; extra == 'all'
Requires-Dist: python-dotenv>=1.0.0; extra == 'all'
Requires-Dist: uvicorn>=0.30.0; extra == 'all'
Provides-Extra: api
Requires-Dist: uvicorn>=0.30.0; extra == 'api'
Provides-Extra: claude
Requires-Dist: anthropic>=0.40.0; extra == 'claude'
Requires-Dist: python-dotenv>=1.0.0; extra == 'claude'
Provides-Extra: groq
Requires-Dist: groq>=0.11.0; extra == 'groq'
Provides-Extra: whisper
Requires-Dist: openai-whisper>=20250625; extra == 'whisper'
